asgardpy/__init__.py
asgardpy/_version.py
asgardpy/conftest.py
asgardpy/py.typed
asgardpy/version.py
asgardpy/analysis/__init__.py
asgardpy/analysis/analysis.py
asgardpy/analysis/step.py
asgardpy/analysis/step_base.py
asgardpy/analysis/tests/__init__.py
asgardpy/analysis/tests/test_analysis_steps.py
asgardpy/base/__init__.py
asgardpy/base/base.py
asgardpy/base/geom.py
asgardpy/base/reduction.py
asgardpy/config/__init__.py
asgardpy/config/generator.py
asgardpy/config/operations.py
asgardpy/config/template.yaml
asgardpy/config/template_model.yaml
asgardpy/config/model_templates/model_template_bpl.yaml
asgardpy/config/model_templates/model_template_bpl2.yaml
asgardpy/config/model_templates/model_template_eclp.yaml
asgardpy/config/model_templates/model_template_ecpl-3fgl.yaml
asgardpy/config/model_templates/model_template_ecpl.yaml
asgardpy/config/model_templates/model_template_ecpl2.yaml
asgardpy/config/model_templates/model_template_fov.yaml
asgardpy/config/model_templates/model_template_lp.yaml
asgardpy/config/model_templates/model_template_pl.yaml
asgardpy/config/model_templates/model_template_pl_ebl.yaml
asgardpy/config/model_templates/model_template_sbpl.yaml
asgardpy/config/model_templates/model_template_secpl.yaml
asgardpy/config/tests/__init__.py
asgardpy/config/tests/test_config.py
asgardpy/data/__init__.py
asgardpy/data/dataset_1d.py
asgardpy/data/dataset_3d.py
asgardpy/data/dl4.py
asgardpy/data/target.py
asgardpy/data/tests/__init__.py
asgardpy/data/tests/test_catalog.py
asgardpy/data/tests/test_dataset1d.py
asgardpy/data/tests/test_dataset3d.py
asgardpy/data/tests/test_gpy_mwl.py
asgardpy/data/tests/test_target.py
asgardpy/gammapy/__init__.py
asgardpy/gammapy/interoperate_models.py
asgardpy/gammapy/read_models.py
asgardpy/gammapy/tests/__init__.py
asgardpy/gammapy/tests/test_xml_model.py
asgardpy/io/__init__.py
asgardpy/io/input_dl3.py
asgardpy/io/io_dl4.py
asgardpy/io/tests/__init__.py
asgardpy/io/tests/test_io.py
asgardpy/stats/__init__.py
asgardpy-0.5.3.dist-info/licenses/LICENSE
asgardpy-0.5.3.dist-info/METADATA
asgardpy-0.5.3.dist-info/WHEEL
asgardpy-0.5.3.dist-info/top_level.txt
asgardpy-0.5.3.dist-info/RECORD
