Metadata-Version: 2.4
Name: asgardpy
Version: 0.5.3
Summary: Gammapy-based pipeline for easy joint analysis of different gamma-ray datasets
Author-email: Chaitanya Priyadarshi <chaitanya.p.astrphys@gmail.com>, Mireia Nievas Rosillo <mnievas.work@gmail.com>
Maintainer-email: Chaitanya Priyadarshi <chaitanya.p.astrphys@gmail.com>
License: Apache-2.0
Project-URL: Homepage, https://github.com/chaimain/asgardpy
Project-URL: Repository, https://github.com/chaimain/asgardpy
Project-URL: Documentation, https://asgardpy.readthedocs.io/en/latest/
Keywords: Astronomy,Gamma-rays,Data analysis
Classifier: Intended Audience :: Science/Research
Classifier: Development Status :: 3 - Alpha
Classifier: License :: OSI Approved :: Apache Software License
Classifier: Programming Language :: Python :: 3.11
Classifier: Programming Language :: Python :: 3.12
Classifier: Programming Language :: Python :: 3.13
Classifier: Topic :: Scientific/Engineering :: Astronomy
Requires-Python: >=3.11
License-File: LICENSE
Requires-Dist: numpy>2.0
Requires-Dist: scipy>=1.12
Requires-Dist: astropy<8.0,>=7.0
Requires-Dist: jupyter
Requires-Dist: gammapy~=1.3
Requires-Dist: regions>0.5
Requires-Dist: matplotlib<3.10,>=3.4
Requires-Dist: seaborn
Requires-Dist: iminuit>=2.8.0
Requires-Dist: ruamel.yaml
Requires-Dist: pre-commit
Requires-Dist: xmltodict
Requires-Dist: tox
Requires-Dist: tqdm
Requires-Dist: pydantic>=2.5
Requires-Dist: towncrier>=24.7
Provides-Extra: dev
Requires-Dist: ruff>=0.9.3; extra == "dev"
Requires-Dist: codespell>=2.4.0; extra == "dev"
Requires-Dist: mypy>=1.14; extra == "dev"
Requires-Dist: isort>=5.13; extra == "dev"
Requires-Dist: types-PyYAML; extra == "dev"
Requires-Dist: pytest>8.0; extra == "dev"
Requires-Dist: pytest-sphinx; extra == "dev"
Requires-Dist: pytest-cov; extra == "dev"
Requires-Dist: build; extra == "dev"
Requires-Dist: setuptools_scm; extra == "dev"
Requires-Dist: Sphinx>=8.0; extra == "dev"
Requires-Dist: furo>=2022.12.7; extra == "dev"
Requires-Dist: myst-parser>=2.0; extra == "dev"
Requires-Dist: sphinx-copybutton>=0.5.0; extra == "dev"
Requires-Dist: sphinx-autobuild>=2021.3.14; extra == "dev"
Requires-Dist: sphinx-autodoc-typehints; extra == "dev"
Requires-Dist: sphinxcontrib-towncrier; extra == "dev"
Requires-Dist: sphinx_changelog; extra == "dev"
Requires-Dist: autodoc_pydantic>=2.1; extra == "dev"
Requires-Dist: packaging; extra == "dev"
Dynamic: license-file
